crossroad/__init__.py
crossroad/config.py
crossroad/api/__init__.py
crossroad/api/main.py
crossroad/cli/__init__.py
crossroad/cli/main.py
crossroad/core/__init__.py
crossroad/core/gc2.py
crossroad/core/logger.py
crossroad/core/m2.py
crossroad/core/plotting.py
crossroad/core/process_ssr_results.py
crossroad/core/slurm_manager.py
crossroad/core/slurm_runner.py
crossroad/core/plots/__init__.py
crossroad/core/plots/category_country_sankey.py
crossroad/core/plots/gene_country_sankey.py
crossroad/core/plots/gene_motif_count_dot_plot.py
crossroad/core/plots/hotspot_plot.py
crossroad/core/plots/motif_conservation_plot.py
crossroad/core/plots/motif_distribution_heatmap.py
crossroad/core/plots/reference_ssr_distribution.py
crossroad/core/plots/relative_abundance_plot.py
crossroad/core/plots/relative_density_plot.py
crossroad/core/plots/ssr_conservation_plot.py
crossroad/core/plots/ssr_gc_plot.py
crossroad/core/plots/ssr_gene_intersect_plot.py
crossroad/core/plots/temporal_faceted_scatter.py
crossroad/core/plots/upset_plot.py
crossroad_cli-0.3.5.dist-info/licenses/LICENSE
crossroad_cli-0.3.5.dist-info/METADATA
crossroad_cli-0.3.5.dist-info/WHEEL
crossroad_cli-0.3.5.dist-info/entry_points.txt
crossroad_cli-0.3.5.dist-info/top_level.txt
crossroad_cli-0.3.5.dist-info/RECORD
