Metadata-Version: 2.4
Name: crossroad-cli
Version: 0.3.5
Summary: A tool for analyzing SSRs in genomic data
Home-page: https://github.com/BioinformaticsOnLine/croSSRoadd
Author: Pranjal Pruthi, Preeti Agarwal
Author-email: "Pranjal Pruthi, Preeti Agarwal" <jnlab.igib@gmail.com>
License: MIT
Classifier: Programming Language :: Python :: 3
Classifier: License :: OSI Approved :: MIT License
Classifier: Operating System :: OS Independent
Requires-Python: >=3.9
License-File: LICENSE
Requires-Dist: numpy
Requires-Dist: fastapi
Requires-Dist: uvicorn
Requires-Dist: python-multipart
Requires-Dist: pandas
Requires-Dist: pydantic
Requires-Dist: requests
Requires-Dist: perf_ssr
Requires-Dist: plotly>=5.18.0
Requires-Dist: plotly-upset-hd>=0.0.2
Requires-Dist: rich
Requires-Dist: colorlog>=6.8.2
Requires-Dist: typer>=0.9.0
Requires-Dist: rich-click>=1.7.0
Requires-Dist: argcomplete>=3.1.1
Requires-Dist: pyarrow
Requires-Dist: upsetplot
Requires-Dist: python-dotenv
Dynamic: author
Dynamic: home-page
Dynamic: license-file
Dynamic: requires-python
